CodernityDB/__init__.py
CodernityDB/database.py
CodernityDB/database_gevent.py
CodernityDB/database_safe_shared.py
CodernityDB/database_super_thread_safe.py
CodernityDB/database_thread_safe.py
CodernityDB/debug_stuff.py
CodernityDB/env.py
CodernityDB/hash_index.py
CodernityDB/index.py
CodernityDB/indexcreator.py
CodernityDB/lfu_cache.py
CodernityDB/lfu_cache_with_lock.py
CodernityDB/migrate.py
CodernityDB/misc.py
CodernityDB/patch.py
CodernityDB/rr_cache.py
CodernityDB/rr_cache_with_lock.py
CodernityDB/sharded_hash.py
CodernityDB/sharded_index.py
CodernityDB/storage.py
CodernityDB/tree_index.py
arabic/.flags
arabic/.gitignore
arabic/Arabic Transliteration Example.ipynb
arabic/ArabicTransliterator.py
arabic/README.md
arabic/__init__.py
arabic/arabic_reshaper.py
arabic/nouns.csv
arabic/phrases.csv
arabic/startup.run
arabic/arabictransliterator.egg-info/PKG-INFO
arabic/arabictransliterator.egg-info/SOURCES.txt
arabic/arabictransliterator.egg-info/dependency_links.txt
arabic/arabictransliterator.egg-info/top_level.txt
arabic/saara/__init__.py
arabic/saara/translit_ar.py
arabic/saara/utils.py
arabic/salang_saara.egg-info/PKG-INFO
arabic/salang_saara.egg-info/SOURCES.txt
arabic/salang_saara.egg-info/dependency_links.txt
arabic/salang_saara.egg-info/requires.txt
arabic/salang_saara.egg-info/top_level.txt
aranasyn/__init__.py
aranasyn/anasyn.py
aranasyn/anasyn2.py
aranasyn/anasynDirect.py
aranasyn/stemmedsynword.py
aranasyn/syn_const.py
aranasyn/synnode.py
arramooz/__init__.py
arramooz/arabicdictionary.py
arramooz/stopwordsdictionaryclass.py
arramooz/wordfreqdictionaryclass.py
arramooz/data/arabicdictionary.sqlite
arramooz/data/arabicdictionary.sqlite.bz2
arramooz/data/nouns_sqliteStructure.sql
arramooz/data/randomtext.txt
arramooz/data/stopwords.sql
arramooz/data/stopwords.sqlite
arramooz/data/stopwords.sqlite.old
arramooz/data/verbs.dict.sqliteStructure.sql
arramooz/data/wordfreq.sqlite
arramooz/data/wordfreq.sqlite.bz2
arramooz/data/wordfreq.sqliteStructure.sql
asmai/__init__.py
asmai/anasem.py
asmai/collocationdictionary.py
asmai/sem_const.py
asmai/sem_const2.py
asmai/semcollocationdictionary.py
collocations/__init__.py
collocations/collocation_const.py
collocations/collocationdictionary.py
collocations/collocations.old.py
collocations/collocations.py
collocations/data/collocations.sqlite
collocations/pyarabic/__init__.py
collocations/pyarabic/arabrepr.py
salang_saara-0.4.2.dist-info/METADATA
salang_saara-0.4.2.dist-info/WHEEL
salang_saara-0.4.2.dist-info/top_level.txt
salang_saara-0.4.2.dist-info/RECORD
